{
  "version": "7",
  "dialect": "postgresql",
  "tables": {
    "public.others": {
      "name": "others",
      "schema": "",
      "columns": {
        "key": {
          "name": "key",
          "type": "varchar(20)",
          "primaryKey": true,
          "notNull": true
        },
        "value": {
          "name": "value",
          "type": "text",
          "primaryKey": false,
          "notNull": true
        }
      },
      "indexes": {},
      "foreignKeys": {},
      "compositePrimaryKeys": {},
      "uniqueConstraints": {},
      "policies": {},
      "isRLSEnabled": false,
      "checkConstraints": {}
    },
    "public.rent_data": {
      "name": "rent_data",
      "schema": "",
      "columns": {
        "id": {
          "name": "id",
          "type": "serial",
          "primaryKey": true,
          "notNull": true
        },
        "amount": {
          "name": "amount",
          "type": "integer",
          "primaryKey": false,
          "notNull": true
        },
        "date": {
          "name": "date",
          "type": "date",
          "primaryKey": false,
          "notNull": true
        },
        "month": {
          "name": "month",
          "type": "date",
          "primaryKey": false,
          "notNull": true
        },
        "user_id": {
          "name": "user_id",
          "type": "integer",
          "primaryKey": false,
          "notNull": false
        }
      },
      "indexes": {},
      "foreignKeys": {
        "rent_data_user_id_users_id_fk": {
          "name": "rent_data_user_id_users_id_fk",
          "tableFrom": "rent_data",
          "columnsFrom": ["user_id"],
          "tableTo": "users",
          "columnsTo": ["id"],
          "onUpdate": "no action",
          "onDelete": "set null"
        }
      },
      "compositePrimaryKeys": {},
      "uniqueConstraints": {},
      "policies": {},
      "isRLSEnabled": false,
      "checkConstraints": {}
    },
    "public.users": {
      "name": "users",
      "schema": "",
      "columns": {
        "id": {
          "name": "id",
          "type": "serial",
          "primaryKey": true,
          "notNull": true
        },
        "name": {
          "name": "name",
          "type": "varchar(15)",
          "primaryKey": false,
          "notNull": true
        },
        "password": {
          "name": "password",
          "type": "char(96)",
          "primaryKey": false,
          "notNull": true
        },
        "is_admin": {
          "name": "is_admin",
          "type": "boolean",
          "primaryKey": false,
          "notNull": true,
          "default": false
        }
      },
      "indexes": {},
      "foreignKeys": {},
      "compositePrimaryKeys": {},
      "uniqueConstraints": {},
      "policies": {},
      "isRLSEnabled": false,
      "checkConstraints": {}
    },
    "public.verification_requests": {
      "name": "verification_requests",
      "schema": "",
      "columns": {
        "id": {
          "name": "id",
          "type": "integer",
          "primaryKey": true,
          "notNull": true
        }
      },
      "indexes": {},
      "foreignKeys": {
        "verification_requests_id_rent_data_id_fk": {
          "name": "verification_requests_id_rent_data_id_fk",
          "tableFrom": "verification_requests",
          "columnsFrom": ["id"],
          "tableTo": "rent_data",
          "columnsTo": ["id"],
          "onUpdate": "no action",
          "onDelete": "cascade"
        }
      },
      "compositePrimaryKeys": {},
      "uniqueConstraints": {},
      "policies": {},
      "isRLSEnabled": false,
      "checkConstraints": {}
    }
  },
  "enums": {},
  "schemas": {},
  "_meta": {
    "schemas": {},
    "tables": {},
    "columns": {}
  },
  "id": "60f8202c-ab49-44d8-87fd-e047096af321",
  "prevId": "75c6508f-f0d5-4dd8-be6e-346df16ea77c",
  "sequences": {},
  "policies": {},
  "views": {},
  "roles": {}
}
